consul_registration/__init__.py
consul_registration/config.py
consul_registration/decorators.py
consul_registration/discovery.py
consul_registration/models.py
consul_registration/service.py
consul_registration/testing/__init__.py
consul_registration/testing/base.py
consul_registration/testing/container.py
consul_registration/testing/models.py
consul_registration-0.1.0.dist-info/METADATA
consul_registration-0.1.0.dist-info/WHEEL
consul_registration-0.1.0.dist-info/RECORD
